PyLinkedinAPI/__init__.py
PyLinkedinAPI/PyLinkedinAPI.py
PyLinkedinAPI-0.1.5.dist-info/DESCRIPTION.rst
PyLinkedinAPI-0.1.5.dist-info/METADATA
PyLinkedinAPI-0.1.5.dist-info/metadata.json
PyLinkedinAPI-0.1.5.dist-info/RECORD
PyLinkedinAPI-0.1.5.dist-info/top_level.txt
PyLinkedinAPI-0.1.5.dist-info/WHEEL
