Metadata-Version: 1.1
Name: PyLinkedinAPI
Version: 0.1.5
Summary: Python library to access Liknkedin API
Home-page: https://github.com/johnidm/PyLinkedinAPI
Author: Johni Douglas Marangon
Author-email: johni.douglas.marangon@gmail.com
License: BSD
Keywords: PyLinkedinAPI
Platform: UNKNOWN
Classifier: Development Status :: 2 - Pre-Alpha
Classifier: Intended Audience :: Developers
Classifier: License :: OSI Approved :: BSD License
Classifier: Natural Language :: English
Classifier: Programming Language :: Python :: 3.4
